subs_webhook/__init__.py
subs_webhook/dependencies.py
subs_webhook/main.py
subs_webhook/py.typed
subs_webhook/webhooks.py
subs_webhook/api/models.py
subs_webhook/api/webhooks.py
subs_webhook/api/dependencies/access_guard.py
subs_webhook/api/dependencies/auth.py
subs_webhook/db/subscriptions/init_db.py
subs_webhook/db/subscriptions/models.py
subs_webhook/providers/pabbly.py
subs_webhook-0.4.0.dist-info/METADATA
subs_webhook-0.4.0.dist-info/WHEEL
subs_webhook-0.4.0.dist-info/RECORD
