Metadata-Version: 2.4
Name: subs-webhook
Version: 0.4.0
Summary: A lightweight, asynchronous FastAPI extension designed to handle SaaS subscriptions, API key management, and plan-based access control. It integrates directly with Pabbly (and is extensible for other providers) to sync subscription statuses and automates access control using Redis caching for high performance.
Requires-Python: >=3.9
Requires-Dist: fastapi>=0.128.0
Requires-Dist: nest-asyncio>=1.6.0
Requires-Dist: redis>=7.0.1
Requires-Dist: sqlalchemy>=2.0.46
